<?xml version="1.0" encoding="utf-8" ?>
<dwsync>
<file name="fontawesome-webfont.eot" server="ftp.servage.net//www/project100/" local="131400458320000000" remote="131497218000000000" />
<file name="fontawesome-webfont.svg" server="ftp.servage.net//www/project100/" local="131400458320000000" remote="131497218000000000" />
<file name="fontawesome-webfont.ttf" server="ftp.servage.net//www/project100/" local="131400458320000000" remote="131497218000000000" />
<file name="fontawesome-webfont.woff" server="ftp.servage.net//www/project100/" local="131400458320000000" remote="131497218000000000" />
<file name="fontawesome-webfont.woff2" server="ftp.servage.net//www/project100/" local="131400458320000000" remote="131497218000000000" />
<file name="FontAwesome.otf" server="ftp.servage.net//www/project100/" local="131400458320000000" remote="131497218000000000" />
<file name="glyphicons-halflings-regular.eot" server="ftp.servage.net//www/project100/" local="131139529820000000" remote="131497218000000000" />
<file name="glyphicons-halflings-regular.svg" server="ftp.servage.net//www/project100/" local="131139529820000000" remote="131497218000000000" />
<file name="glyphicons-halflings-regular.ttf" server="ftp.servage.net//www/project100/" local="131139529820000000" remote="131497218600000000" />
<file name="glyphicons-halflings-regular.woff" server="ftp.servage.net//www/project100/" local="131139529820000000" remote="131497218600000000" />
<file name="glyphicons-halflings-regular.woff2" server="ftp.servage.net//www/project100/" local="131139529820000000" remote="131497218600000000" />
</dwsync>